chatcli_gptx-1.0.1.dist-info/licenses/LICENSE
chatgpt_cli/__main__.py
chatgpt_cli/main.py
chatcli_gptx-1.0.1.dist-info/METADATA
chatcli_gptx-1.0.1.dist-info/WHEEL
chatcli_gptx-1.0.1.dist-info/entry_points.txt
chatcli_gptx-1.0.1.dist-info/top_level.txt
chatcli_gptx-1.0.1.dist-info/RECORD
