Metadata-Version: 2.4
Name: chatcli-gptx
Version: 1.0.1
Summary: A flexible command-line tool for interacting with OpenAI's ChatGPT API
Author-email: Andrew Hamilton <drew@hamiltonhaus.tech>
License: MIT
Project-URL: Homepage, https://www.hamiltonhaus.tech
Project-URL: Repository, https://github.com/hamiltonhaustech/chatgpt_cli
Project-URL: Issues, https://github.com/hamiltonhaustech/chatgpt_cli/issues
Requires-Python: >=3.8
License-File: LICENSE
Requires-Dist: openai>=1.0
Requires-Dist: python-dotenv>=0.21
Requires-Dist: colorama>=0.4
Dynamic: license-file
